clivy/__init__.py
clivy/core.py
clivy-0.1.0.dist-info/METADATA
clivy-0.1.0.dist-info/WHEEL
clivy-0.1.0.dist-info/licenses/LICENSE
clivy-0.1.0.dist-info/RECORD
