Metadata-Version: 2.4
Name: clivy
Version: 0.1.0
Summary: A Python package for CLI utilities
Project-URL: Homepage, https://github.com/ChromaDevs/clivy
Project-URL: Bug Tracker, https://github.com/ChromaDevs/clivy/issues
License-File: LICENSE
Classifier: License :: OSI Approved :: MIT License
Classifier: Operating System :: OS Independent
Classifier: Programming Language :: Python :: 3
Requires-Python: >=3.8
